sweetpie/__init__.py
sweetpie/readers.py
sweetpie/sequence_processor.py
sweetpie/tokenizers.py
tests/__init__.py
tests/readers_test.py
tests/sequence_processor_test.py
sweetpie-0.1.1.dist-info/LICENSE
sweetpie-0.1.1.dist-info/METADATA
sweetpie-0.1.1.dist-info/WHEEL
sweetpie-0.1.1.dist-info/top_level.txt
sweetpie-0.1.1.dist-info/RECORD
